logopy/__init__.py
logopy/errors.py
logopy/gui.py
logopy/procedure.py
logopy/svgturtle.py
logopy/trig.py
logopy/resources/html/README.rst
logopy/resources/html/svg.html.jinja2
logopy/resources/html/vivus.min.js
logopy-0.0.4.data/scripts/logopycli.py
logopy-0.0.4.dist-info/LICENSE.txt
logopy-0.0.4.dist-info/METADATA
logopy-0.0.4.dist-info/WHEEL
logopy-0.0.4.dist-info/top_level.txt
logopy-0.0.4.dist-info/RECORD
